cerebrixos_route/__init__.py
cerebrixos_route/cli.py
cerebrixos_route/main.py
cerebrixos_route-0.6.0.dist-info/METADATA
cerebrixos_route-0.6.0.dist-info/WHEEL
cerebrixos_route-0.6.0.dist-info/entry_points.txt
cerebrixos_route-0.6.0.dist-info/top_level.txt
cerebrixos_route-0.6.0.dist-info/RECORD
