Metadata-Version: 2.4
Name: CerebrixOS-Route
Version: 0.6.0
Summary: CerebrixOS router exposes internal private services via zero-trust networking
Author-email: CerebrixOS <hello@ockhamlabs.ai>
License: MIT
Requires-Python: >=3.8
Requires-Dist: requests
Requires-Dist: tqdm
Requires-Dist: psutil
Requires-Dist: packaging
Requires-Dist: PyJWT
Requires-Dist: colorama
Requires-Dist: jinja2
Requires-Dist: distro
Requires-Dist: pyyaml
